.gitignore
LICENSE
MANIFEST.in
README.rst
requirements-dev.txt
setup.py
girder_metadata_links/__init__.py
girder_metadata_links.egg-info/PKG-INFO
girder_metadata_links.egg-info/SOURCES.txt
girder_metadata_links.egg-info/dependency_links.txt
girder_metadata_links.egg-info/entry_points.txt
girder_metadata_links.egg-info/not-zip-safe
girder_metadata_links.egg-info/requires.txt
girder_metadata_links.egg-info/top_level.txt
girder_metadata_links/web_client/link.pug
girder_metadata_links/web_client/main.js
girder_metadata_links/web_client/package.json