Metadata-Version: 1.1
Name: girder-metadata-links
Version: 0.3.0
Summary: Renders hyperlinks to Girder resources from metadata values
Home-page: https://github.com/girder/girder_metadata_links
Author: Zach Mullen
Author-email: zach.mullen@kitware.com
License: Apache Software License 2.0
Keywords: girder-plugin,girder_metadata_links
Platform: UNKNOWN
Classifier: Development Status :: 2 - Pre-Alpha
Classifier: License :: OSI Approved :: Apache Software License
Classifier: Natural Language :: English
Classifier: Programming Language :: Python :: 2
Classifier: Programming Language :: Python :: 2.7
Classifier: Programming Language :: Python :: 3
Classifier: Programming Language :: Python :: 3.5
Classifier: Programming Language :: Python :: 3.6
